[{"s": "trikli-moyushchij-pylesos-kak-polzovatsya", "t": "Моющий пылесос Trikki: полная инструкция по использованию и уходу", "i": "💧", "c": "moyushchie-sistemy"}, {"s": "tresnul-shlang-ot-pylesosa-kak-otremontirovat", "t": "Треснул шланг пылесоса: 5 способов ремонта своими руками", "i": "🔧", "c": "remont-i-zapchasti"}, {"s": "truba-dlya-pylesosa-chem-zamenit", "t": "Труба для пылесоса чем заменить: DIY-решения и аналоги", "i": "🔧", "c": "remont-i-zapchasti"}, {"s": "truba-teleskopicheskaya-dlya-pylesosa-samsung-kak-pochinit", "t": "Чиним телескопическую трубу пылесоса Samsung: пошаговая инструкция", "i": "🔧", "c": "remont-i-zapchasti"}, {"s": "truba-pylesosa-teleskopicheskaya-kak-otremontirovat", "t": "Как отремонтировать телескопическую трубу пылесоса: пошаговая инструкция", "i": "🔧", "c": "remont-i-zapchasti"}]