[{"s": "vilka-dlya-pylesosa-skolko-amper", "t": "Вилка для пылесоса: сколько ампер и какой стандарт использовать", "i": "🔧", "c": "remont-i-zapchasti"}, {"s": "video-kak-chistit-bassejn-ruchnym-pylesosom", "t": "Как чистить бассейн ручным пылесосом: Пошаговая инструкция и видео", "i": "🐈", "c": "uborka-s-zhivotnymi"}, {"s": "video-kak-rabotaet-robot-pylesos-xiaomi", "t": "Видео: как работает робот-пылесос Xiaomi — принцип действия и обзор", "i": "🤖", "c": "roboty-pylesosy"}, {"s": "vitek-pylesos-kak-vytashchit-meshok", "t": "Как вытащить мешок из пылесоса Vitek: пошаговая инструкция", "i": "✨", "c": "ukhod-za-tekhnikoj"}, {"s": "video-kak-razobrat-dvigatel-pylesosa-samsung", "t": "Видео-инструкция: как разобрать двигатель пылесоса Samsung", "i": "🔧", "c": "remont-i-zapchasti"}, {"s": "video-kak-vybrat-pylesos", "t": "Как выбрать пылесос: экспертный гид по типу, мощности и фильтрации", "i": "🏠", "c": "vybor-dlya-doma"}, {"s": "video-moyushchij-pylesos-tomas-dlya-vlazhnoj-uborki-kak-sobrat", "t": "Как собрать видео моющий пылесос Thomas: пошаговая инструкция", "i": "💧", "c": "moyushchie-sistemy"}, {"s": "video-kak-rabotaet-robot-pylesos-v-bassejne", "t": "Как работает робот-пылесос для бассейна: принцип действия и видео", "i": "🤖", "c": "roboty-pylesosy"}, {"s": "vitek-pylesos-kak-vstavlyaetsya", "t": "Витек пылесос: как вставляется шланг, насадка и мешок", "i": "✨", "c": "ukhod-za-tekhnikoj"}, {"s": "video-pro-pylesos-chto-tam-ego-nozhki-vklyuchayut", "t": "Видео: почему у пылесоса включаются ножки и как это работает", "i": "🤖", "c": "roboty-pylesosy"}, {"s": "videt-vo-sne-pylesos-k-chemu-eto", "t": "К чему снится пылесос: толкование сна по разным сонникам", "i": "📁", "c": "drugoe"}, {"s": "video-gde-deti-pylesosyat", "t": "Видео с детьми и пылесосом: польза, безопасность и выбор техники", "i": "🤖", "c": "roboty-pylesosy"}, {"s": "video-kak-podklyuchitsya-k-robotu-pylesosu", "t": "Как подключить робот-пылесос к Wi-Fi: пошаговая инструкция 2026", "i": "📱", "c": "nastrojki-i-podklyuchenie"}, {"s": "video-kak-alisa-rugaetsya-s-pylesosom", "t": "Видео: Алиса ругается с роботом-пылесосом — юмор и сценарии", "i": "🤖", "c": "roboty-pylesosy"}, {"s": "video-kak-chistit-bassejn-pylesosom", "t": "Как чистить бассейн пылесосом: видео-инструкция и советы", "i": "💧", "c": "moyushchie-sistemy"}, {"s": "vintik-shpuntik-i-pylesos-chemu-uchit-rasskaz", "t": "Винтик, Шпунтик и пылесос: чему учит рассказ Э.Успенского", "i": "🔧", "c": "remont-i-zapchasti"}, {"s": "vitek-pylesos-che-proizvodstvo", "t": "Витек пылесос: чье производство, страна-изготовитель и качество", "i": "⚖️", "c": "sravnenie-brendov"}, {"s": "video-kak-alisa-porugalas-s-pylesosom", "t": "Видео: почему Алиса поругалась с пылесосом? Разбор ситуации", "i": "📱", "c": "nastrojki-i-podklyuchenie"}, {"s": "video-moyushchij-pylesos-kerkher-kak-polzovatsya", "t": "Как пользоваться моющим пылесосом Kärcher: Полная инструкция", "i": "💧", "c": "moyushchie-sistemy"}, {"s": "video-kak-sdelat-pylesos-svoimi-rukami", "t": "Видео: как сделать пылесос своими руками из подручных средств", "i": "🔧", "c": "remont-i-zapchasti"}, {"s": "video-kak-materitsya-robot-pylesos", "t": "Почему робот-пылесос «матерится»: разбор ошибок и звуковых сигналов", "i": "⚠️", "c": "problemy-i-resheniya"}, {"s": "vizzhit-pylesos-pochemu", "t": "Почему визжит пылесос: причины шума и способы ремонта", "i": "⚠️", "c": "problemy-i-resheniya"}, {"s": "video-kak-nastroit-robot-pylesos-xiaomi", "t": "Как настроить робот-пылесос Xiaomi: полное руководство и видео", "i": "🤖", "c": "roboty-pylesosy"}, {"s": "video-kak-razbirayut-pylesos", "t": "Видео: как правильно разобрать пылесос своими руками | Пошагово", "i": "🔧", "c": "remont-i-zapchasti"}, {"s": "video-kak-rabotaet-robot-pylesos-polaris", "t": "Как работает робот-пылесос Polaris: принцип действия и видеообзор", "i": "🤖", "c": "roboty-pylesosy"}, {"s": "virtualnaya-stena-dlya-robota-pylesosa-chto-eto", "t": "Виртуальная стена для робота-пылесоса: что это и как работает", "i": "🤖", "c": "roboty-pylesosy"}, {"s": "vitek-pylesos-s-akvafiltrom-kak-razobrat", "t": "Как разобрать пылесос Vitek с аквафильтром: полная инструкция по разборке", "i": "🔧", "c": "remont-i-zapchasti"}, {"s": "video-kak-vklyuchit-robot-pylesos-polaris", "t": "Как включить робот-пылесос Polaris: полная инструкция", "i": "🤖", "c": "roboty-pylesosy"}, {"s": "video-gde-kot-otodvigaet-lapoj-robot-pylesos", "t": "Видео: кот отодвигает лапой робот пылесос — причины и реакция", "i": "🐈", "c": "uborka-s-zhivotnymi"}, {"s": "vitek-pylesos-kak-vklyuchit", "t": "Как включить пылесос Витек: инструкции для всех моделей", "i": "📱", "c": "nastrojki-i-podklyuchenie"}, {"s": "video-gde-rugayutsya-robot-pylesos-i-alisa", "t": "Видео: почему робот-пылесос и Алиса ругаются и как это исправить", "i": "📱", "c": "nastrojki-i-podklyuchenie"}, {"s": "video-gde-robot-pylesos-vezet-bokal-vina", "t": "Робот-пылесос с бокалом вина: тест устойчивости и стабильности", "i": "🤖", "c": "roboty-pylesosy"}, {"s": "video-gde-robot-pylesos-vezet-vino", "t": "Робот-пылесос везет вино: миф, виртуальный розыгрыш или реальность?", "i": "🏠", "c": "vybor-dlya-doma"}, {"s": "video-kak-snyat-shchetki-s-robota-pylesosa", "t": "Видео: как снять щетки с робота-пылесоса за 5 минут", "i": "✨", "c": "ukhod-za-tekhnikoj"}, {"s": "video-kak-rabotaet-robot-pylesos-xiaomi-moyushchij", "t": "Как работает моющий робот-пылесос Xiaomi: принцип действия и видео обзор", "i": "💧", "c": "moyushchie-sistemy"}, {"s": "video-gde-robot-pylesos-rugaetsya-matom", "t": "Робот-пылесос ругается матом: правда, мифы и настройки голоса", "i": "📱", "c": "nastrojki-i-podklyuchenie"}, {"s": "video-gde-alisa-irobot-pylesos", "t": "Видео обзор: роботы-пылесосы iRobot и Алиса — работа, управление и тесты", "i": "📱", "c": "nastrojki-i-podklyuchenie"}, {"s": "video-robot-pylesos-smotret-kak-rabotaet-zvuk", "t": "Видео робот-пылесос: как работает, звук и разбор шума", "i": "🤖", "c": "roboty-pylesosy"}, {"s": "video-kak-polzovatsya-moyushchim-pylesosom-tomas-oranzhevyj", "t": "Видео-гайд: как пользоваться моющим пылесосом Thomas оранжевый", "i": "💧", "c": "moyushchie-sistemy"}, {"s": "video-kak-sdelat-pylesos-dlya-bassejna", "t": "Видео: как сделать пылесос для бассейна своими руками", "i": "🔧", "c": "remont-i-zapchasti"}, {"s": "video-kak-sdelat-samodelnyj-pylesos", "t": "Видео: как сделать самодельный пылесос своими руками", "i": "🔧", "c": "remont-i-zapchasti"}, {"s": "video-kak-papa-pylesosom-delaet-khvostik-dochke", "t": "Видео: как папа пылесосом делает хвостик дочке — техника и факты", "i": "⚠️", "c": "problemy-i-resheniya"}, {"s": "video-kak-rabotaet-robot-pylesos-redmond", "t": "Как работает робот-пылесос Redmond: принцип действия и технологии уборки", "i": "🤖", "c": "roboty-pylesosy"}, {"s": "video-kak-possorilis-alisa-s-pylesosom", "t": "Видео: как поссорились Алиса с пылесосом — разбор ситуаций и решений", "i": "📱", "c": "nastrojki-i-podklyuchenie"}, {"s": "video-kak-vybrat-robot-pylesos", "t": "Видео: Как выбрать робот-пылесос — Полный гайд по функциям и типам", "i": "🏠", "c": "vybor-dlya-doma"}, {"s": "video-kak-nastroit-robot-pylesos", "t": "Видео как настроить робот пылесос: Пошаговая инструкция по Wi-Fi и карте", "i": "📱", "c": "nastrojki-i-podklyuchenie"}, {"s": "video-kak-razobrat-pylesos-samsung", "t": "Как разобрать пылесос Samsung: видео-инструкция и гайд по ремонту", "i": "🔧", "c": "remont-i-zapchasti"}, {"s": "vintik-shpuntik-i-pylesos-chemu-uchit", "t": "Винтик, Шпунтик и Пылесос: чему учит книга и мультфильм", "i": "🔧", "c": "remont-i-zapchasti"}, {"s": "video-gde-robot-pylesos-rugaetsya-s-kolonkoj", "t": "Видео где робот пылесос ругается с колонкой: юмор, баги и сценарии", "i": "📱", "c": "nastrojki-i-podklyuchenie"}, {"s": "video-gde-alisa-ssoritsya-s-pylesosom", "t": "Видео ссоры Алисы и пылесоса: смешные моменты, сценарии и реакция", "i": "📱", "c": "nastrojki-i-podklyuchenie"}, {"s": "videokarta-shumit-kak-pylesos", "t": "Видеокарта шумит как пылесос: Причины и способы устранения", "i": "🔧", "c": "remont-i-zapchasti"}, {"s": "video-gde-alisa-sporit-s-pylesosom-robotom", "t": "Видео Алиса спорит с роботом-пылесосом: Сценарии и сборка", "i": "📱", "c": "nastrojki-i-podklyuchenie"}, {"s": "video-kak-polzovatsya-pylesosom-tomson", "t": "Видео-инструкция: как правильно пользоваться пылесосом Thomson", "i": "✨", "c": "ukhod-za-tekhnikoj"}, {"s": "video-kak-pylesos-zasasyvaet-yubku", "t": "Почему пылесос засасывает юбку: физика, типы насадок и защита", "i": "⚠️", "c": "problemy-i-resheniya"}, {"s": "video-kak-robot-pylesos-rugaetsya", "t": "Видео как робот-пылесос ругается: причины, модели и решения", "i": "⚠️", "c": "problemy-i-resheniya"}, {"s": "virtualnaya-stena-robot-pylesos-chto-eto", "t": "Виртуальная стена для робота-пылесоса: как работает и зачем нужна", "i": "📱", "c": "nastrojki-i-podklyuchenie"}, {"s": "video-gde-alisa-robot-pylesos", "t": "Видео об Алисе: тесты, обзоры и уборка роботом-пылесосом с Яндекс", "i": "🤖", "c": "roboty-pylesosy"}, {"s": "video-kak-alisa-razgovarivaet-s-pylesosom-robotom", "t": "Видео: как Алиса общается с роботом-пылесосом — обзор функций", "i": "📱", "c": "nastrojki-i-podklyuchenie"}, {"s": "vitek-1834-pylesos-s-akvafiltrom-kak-snyat-kryshku", "t": "Как снять крышку с пылесоса Vitek 1834: пошаговая инструкция", "i": "🔧", "c": "remont-i-zapchasti"}, {"s": "video-kakim-luchshe-pylesosom-chistit-divan", "t": "Видео: каким пылесосом лучше чистить диван — разбор методов и моделей", "i": "💧", "c": "moyushchie-sistemy"}, {"s": "video-gde-alisa-razgovarivaet-s-pylesosom", "t": "Видео где Алиса говорит с пылесосом: обзор интеграции и управление", "i": "🤖", "c": "roboty-pylesosy"}, {"s": "video-obzor-kak-rabotaet-robot-pylesos", "t": "Видео обзор: как работает робот пылесос внутри и снаружи", "i": "🤖", "c": "roboty-pylesosy"}, {"s": "video-kak-rabotaet-pylesos-dlya-bassejna-inteks", "t": "Как работает пылесос для бассейна Intex: принцип действия и видео", "i": "📱", "c": "nastrojki-i-podklyuchenie"}, {"s": "video-pro-pylesos-chto-tam-ego-nozhki-vklyuchayut-nu", "t": "Ножки в пылесосе: что это, как работают и зачем нужны", "i": "🔧", "c": "remont-i-zapchasti"}, {"s": "video-kak-ty-rugaeshsya-s-pylesosom", "t": "Видео: как ругаться с пылесосом — смешные моменты и советы", "i": "⚠️", "c": "problemy-i-resheniya"}, {"s": "vitek-2000w-pylesos-kak-snyat-musorosbornik", "t": "Как снять мусоросборник пылесоса Vitek 2000W: пошаговая инструкция", "i": "✨", "c": "ukhod-za-tekhnikoj"}, {"s": "video-gde-robot-pylesos-razmazal", "t": "Видео где робот-пылесос размазал: ТОП-5 провалов и как избежать", "i": "⚠️", "c": "problemy-i-resheniya"}, {"s": "video-kak-polzovatsya-pylesosom-tomas", "t": "Видео-инструкция: как правильно пользоваться пылесосом Thomas", "i": "💧", "c": "moyushchie-sistemy"}, {"s": "video-kak-sdelat-robot-pylesos-svoimi-rukami", "t": "Видео-гид: как сделать робот-пылесос своими руками из подручных средств", "i": "🤖", "c": "roboty-pylesosy"}]