[{"s": "vypryamit-shchetki-u-robota-pylesosa-kak", "t": "Как выпрямить щетки робота-пылесоса: Инструкция и методы восстановления", "i": "🔧", "c": "remont-i-zapchasti"}, {"s": "vyigrat-robot-pylesos-gde-mozhno", "t": "Где можно выиграть робот-пылесос: реальные способы и обзоры", "i": "🤖", "c": "roboty-pylesosy"}, {"s": "vyduvayushchij-pylesos-kak-nazyvaetsya", "t": "Выдувающий пылесос: как называется, что это и зачем нужен", "i": "🏥", "c": "spetsnaznacheniya"}, {"s": "vyletaet-zadnij-filtr-iz-pylesosa-samsung-chto-delat", "t": "Вылетает задний фильтр из пылесоса Samsung: причины и способы fix", "i": "🔧", "c": "remont-i-zapchasti"}, {"s": "vyklyuchilsya-pylesos-i-ne-vklyuchaetsya-chto-delat", "t": "Пылесос выключился и не включается: диагностика, причины и ремонт", "i": "⚠️", "c": "problemy-i-resheniya"}, {"s": "vybrat-robot-pylesos-xiaomi-s-vlazhnoj-uborkoj-kak-vybrat", "t": "Как выбрать робот-пылесос Xiaomi с влажной уборкой: полный гид", "i": "🤖", "c": "roboty-pylesosy"}, {"s": "vybrat-robot-pylesos-v-2022-kakoj", "t": "Как выбрать робот-пылесос в 2022: полный гид по моделям и функциям", "i": "🏠", "c": "vybor-dlya-doma"}, {"s": "vybrat-robot-pylesos-na-chto-obratit-vnimanie", "t": "Как выбрать робот-пылесос: основные критерии и советы эксперта", "i": "🏠", "c": "vybor-dlya-doma"}, {"s": "vykhodnoj-filtr-dlya-pylesosa-samsung-kak-ustanovit", "t": "Как установить выходной фильтр для пылесоса Samsung: пошаговая инструкция", "i": "🌬️", "c": "filtry-i-raskhodniki"}, {"s": "vybrat-robota-pylesosa-luchshe-kakuyu", "t": "Как выбрать лучшего робота-пылесоса: полное руководство по характеристикам", "i": "🏠", "c": "vybor-dlya-doma"}, {"s": "vybrat-robot-pylesos-po-parametram-dlya-doma-kakim", "t": "Как выбрать робот-пылесос для дома: главные параметры и советы", "i": "🤖", "c": "roboty-pylesosy"}, {"s": "vykhodnoj-filtr-dlya-pylesosa-chto-eto", "t": "Выходной фильтр для пылесоса: что это, виды и замена", "i": "🌬️", "c": "filtry-i-raskhodniki"}, {"s": "vytyazhka-kak-pylesos", "t": "Вытяжка как пылесос: можно ли использовать вытяжку для уборки", "i": "⚠️", "c": "problemy-i-resheniya"}, {"s": "vyletaet-filtr-iz-pylesosa-chto-delat", "t": "Фильтр вылетает из пылесоса: 5 причин поломки и способы fix", "i": "🔧", "c": "remont-i-zapchasti"}, {"s": "vysokaya-moshchnost-vsasyvaniya-u-pylesosa-dlya-doma-kakaya", "t": "Мощность всасывания пылесоса: какая норма для дома, Вт и АВт", "i": "🏠", "c": "vybor-dlya-doma"}, {"s": "vysosala-kak-pylesos", "t": "Высосала как пылесос: причины, диагностика и устранение проблем", "i": "⚠️", "c": "problemy-i-resheniya"}, {"s": "vytyazhka-manikyurnaya-chem-otlichaetsya-ot-pylesosa", "t": "Вытяжка или пылесос для маникюра: главные отличия и выбор", "i": "🏥", "c": "spetsnaznacheniya"}, {"s": "vypusknoj-filtr-dlya-pylesosa-samsung-dlya-chego-nuzhen", "t": "Выпускной фильтр для пылесоса Samsung: зачем нужен и как менять", "i": "🌬️", "c": "filtry-i-raskhodniki"}, {"s": "vyklyuchaetsya-robot-pylesos-xiaomi-vo-vremya-uborki-i-ne-vklyuchaetsya-pochemu", "t": "Робот пылесос Xiaomi выключается во время уборки: причины и fix", "i": "🤖", "c": "roboty-pylesosy"}, {"s": "vyletaet-filtr-iz-pylesosa-samsung-chto-delat-v-domashnikh-usloviyakh", "t": "Вылетает фильтр из пылесоса Samsung: причины и ремонт своими руками", "i": "🌬️", "c": "filtry-i-raskhodniki"}, {"s": "vybrat-robot-pylesos-v-2023-godu-kakoj", "t": "Как выбрать робот-пылесос в 2023 году: гид по моделям и функциям", "i": "🏠", "c": "vybor-dlya-doma"}, {"s": "vybor-pylesosa-kakoj-luchshe", "t": "Какой пылесос лучше выбрать: полный гайд по типам и брендам", "i": "🏠", "c": "vybor-dlya-doma"}, {"s": "vytyazhka-ili-pylesos-dlya-manikyura-chto-luchshe", "t": "Вытяжка или пылесос для маникюра: что выбрать для безопасной работы", "i": "⚖️", "c": "sravnenie-brendov"}, {"s": "vybrat-besprovodnoj-pylesos-vertikalnyj-kakoj-luchshe", "t": "Как выбрать беспроводной вертикальный пылесос: ТОП-факторы 2026", "i": "🧹", "c": "vertikalnye-modeli"}, {"s": "vyklyuchatel-sfc-na-pylesose-chto-eto", "t": "Выключатель SFC на пылесосе: что это и как работает", "i": "🔧", "c": "remont-i-zapchasti"}, {"s": "vybiraem-pylesos-ili-kak-pereschitat-vt-v-kpa-i-mbar", "t": "Ватты в Паскали: как выбрать мощный пылесос и не ошибиться в расчетах", "i": "⚖️", "c": "sravnenie-brendov"}, {"s": "vybor-pylesosa-kak", "t": "Как правильно выбрать пылесос для квартиры: гид по типам и характеристикам", "i": "🏠", "c": "vybor-dlya-doma"}, {"s": "vybrat-avtomobilnyj-pylesos-kakoj-luchshe", "t": "Как выбрать автомобильный пылесос: рейтинг лучших моделей 2026", "i": "🚗", "c": "avtomobilnye-pylesosy"}, {"s": "vyduv-pylesosa-chto-eto", "t": "Выдув пылесоса: функции, проверка герметичности и использование", "i": "✨", "c": "ukhod-za-tekhnikoj"}]